openscvx/__init__.py
openscvx/_version.py
openscvx/config.py
openscvx/problem.py
openscvx/algorithms/__init__.py
openscvx/algorithms/autotuning.py
openscvx/algorithms/base.py
openscvx/algorithms/optimization_results.py
openscvx/algorithms/penalized_trust_region.py
openscvx/discretization/__init__.py
openscvx/discretization/discretization.py
openscvx/expert/__init__.py
openscvx/expert/byof.py
openscvx/expert/lowering.py
openscvx/expert/validation.py
openscvx/init/__init__.py
openscvx/init/interpolation.py
openscvx/integrators/__init__.py
openscvx/integrators/runge_kutta.py
openscvx/lowered/__init__.py
openscvx/lowered/cvxpy_constraints.py
openscvx/lowered/cvxpy_variables.py
openscvx/lowered/dynamics.py
openscvx/lowered/jax_constraints.py
openscvx/lowered/parameters.py
openscvx/lowered/problem.py
openscvx/lowered/unified.py
openscvx/plotting/__init__.py
openscvx/plotting/plotting.py
openscvx/plotting/scp_iteration.py
openscvx/plotting/viser/__init__.py
openscvx/plotting/viser/animated.py
openscvx/plotting/viser/plotly_integration.py
openscvx/plotting/viser/primitives.py
openscvx/plotting/viser/scp.py
openscvx/plotting/viser/server.py
openscvx/propagation/__init__.py
openscvx/propagation/post_processing.py
openscvx/propagation/propagation.py
openscvx/solvers/__init__.py
openscvx/solvers/base.py
openscvx/solvers/ptr_solver.py
openscvx/symbolic/__init__.py
openscvx/symbolic/augmentation.py
openscvx/symbolic/builder.py
openscvx/symbolic/constraint_set.py
openscvx/symbolic/hashing.py
openscvx/symbolic/lower.py
openscvx/symbolic/preprocessing.py
openscvx/symbolic/problem.py
openscvx/symbolic/time.py
openscvx/symbolic/unified.py
openscvx/symbolic/expr/__init__.py
openscvx/symbolic/expr/arithmetic.py
openscvx/symbolic/expr/array.py
openscvx/symbolic/expr/constraint.py
openscvx/symbolic/expr/control.py
openscvx/symbolic/expr/expr.py
openscvx/symbolic/expr/linalg.py
openscvx/symbolic/expr/logic.py
openscvx/symbolic/expr/math.py
openscvx/symbolic/expr/spatial.py
openscvx-0.4.0.dist-info/licenses/LICENSE
openscvx-0.4.0.dist-info/METADATA
openscvx-0.4.0.dist-info/WHEEL
openscvx-0.4.0.dist-info/top_level.txt
openscvx-0.4.0.dist-info/RECORD
