Metadata-Version: 2.4
Name: openscvx
Version: 0.4.0
Summary: A general Python-based successive convexification implementation which uses a JAX backend.
Author-email: Chris Hayner and Griffin Norris <haynec@uw.edu>
License: Apache Software License
Project-URL: Homepage, https://openscvx.github.io/openscvx/
Classifier: Programming Language :: Python :: 3
Classifier: License :: OSI Approved :: Apache Software License
Requires-Python: >=3.9
License-File: LICENSE
Requires-Dist: cvxpy==1.7.5
Requires-Dist: qoco
Requires-Dist: numpy
Requires-Dist: jax
Requires-Dist: plotly
Requires-Dist: termcolor
Requires-Dist: diffrax
Requires-Dist: absl-py
Requires-Dist: flatbuffers
Requires-Dist: viser
Requires-Dist: matplotlib
Provides-Extra: gui
Requires-Dist: pyqtgraph; extra == "gui"
Requires-Dist: PyQt5; extra == "gui"
Requires-Dist: scipy; extra == "gui"
Requires-Dist: PyOpenGL; extra == "gui"
Requires-Dist: PyOpenGL_accelerate; extra == "gui"
Provides-Extra: cvxpygen
Requires-Dist: cvxpygen; extra == "cvxpygen"
Requires-Dist: qocogen; extra == "cvxpygen"
Provides-Extra: stl
Requires-Dist: stljax; extra == "stl"
Provides-Extra: lie
Requires-Dist: jaxlie; extra == "lie"
Provides-Extra: test
Requires-Dist: pytest; extra == "test"
Requires-Dist: scipy; extra == "test"
Requires-Dist: jaxlie; extra == "test"
Dynamic: license-file
